hc_mcp_jira/__init__.py
hc_mcp_jira/server.py
hc_mcp_jira-2025.3.9.dist-info/METADATA
hc_mcp_jira-2025.3.9.dist-info/WHEEL
hc_mcp_jira-2025.3.9.dist-info/entry_points.txt
hc_mcp_jira-2025.3.9.dist-info/RECORD
