Metadata-Version: 2.4
Name: hc-mcp-jira
Version: 2025.3.9
Summary: HC MCP server for Jira integration
Author-email: Erik Meinders <erik@easytocloud.com>
Requires-Python: >=3.10
Requires-Dist: jira>=3.5.1
Requires-Dist: mcp-config-manager>=0.1.1
Requires-Dist: mcp>=1.2.0
